adbc_driver_duckdb/__init__.py
adbc_driver_duckdb/dbapi.py
duckdb/__init__.py
duckdb/bytes_io_wrapper.py
duckdb/duckdb.cpython-39-aarch64-linux-gnu.so
duckdb/filesystem.py
duckdb/udf.py
duckdb/experimental/__init__.py
duckdb/experimental/spark/LICENSE
duckdb/experimental/spark/__init__.py
duckdb/experimental/spark/_globals.py
duckdb/experimental/spark/_typing.py
duckdb/experimental/spark/conf.py
duckdb/experimental/spark/context.py
duckdb/experimental/spark/exception.py
duckdb/experimental/spark/errors/__init__.py
duckdb/experimental/spark/errors/error_classes.py
duckdb/experimental/spark/errors/utils.py
duckdb/experimental/spark/errors/exceptions/__init__.py
duckdb/experimental/spark/errors/exceptions/base.py
duckdb/experimental/spark/sql/__init__.py
duckdb/experimental/spark/sql/_typing.py
duckdb/experimental/spark/sql/catalog.py
duckdb/experimental/spark/sql/column.py
duckdb/experimental/spark/sql/conf.py
duckdb/experimental/spark/sql/dataframe.py
duckdb/experimental/spark/sql/functions.py
duckdb/experimental/spark/sql/group.py
duckdb/experimental/spark/sql/readwriter.py
duckdb/experimental/spark/sql/session.py
duckdb/experimental/spark/sql/streaming.py
duckdb/experimental/spark/sql/type_utils.py
duckdb/experimental/spark/sql/types.py
duckdb/experimental/spark/sql/udf.py
duckdb/functional/__init__.py
duckdb/query_graph/__main__.py
duckdb/typing/__init__.py
duckdb/value/constant.py
duckdb-stubs/__init__.pyi
duckdb-stubs/functional/__init__.pyi
duckdb-stubs/typing/__init__.pyi
duckdb-stubs/value/__init__.pyi
duckdb-stubs/value/constant/__init__.pyi
duckdb-1.3.2.dist-info/METADATA
duckdb-1.3.2.dist-info/WHEEL
duckdb-1.3.2.dist-info/top_level.txt
duckdb-1.3.2.dist-info/RECORD
