Metadata-Version: 2.4
Name: duckdb
Version: 1.3.2
Summary: DuckDB in-process database
Author-email: Hannes Muehleisen <hannes@cwi.nl>
Project-URL: Documentation, https://duckdb.org/docs/stable/clients/python/overview
Project-URL: Source, https://github.com/duckdb/duckdb/blob/main/tools/pythonpkg
Project-URL: Issues, https://github.com/duckdb/duckdb/issues
Project-URL: Changelog, https://github.com/duckdb/duckdb/releases
Keywords: DuckDB,Database,SQL,OLAP
Classifier: Topic :: Database :: Database Engines/Servers
Classifier: Intended Audience :: Developers
Classifier: License :: OSI Approved :: MIT License
Requires-Python: >=3.7.0
